{
  "name": "Cursor Agent Environment",
  "image": "mcr.microsoft.com/devcontainers/base:ubuntu",
  "features": {
    "ghcr.io/devcontainers/features/common-utils:1": {
      "configureZshAsDefaultShell": true
    },
    "ghcr.io/devcontainers/features/common-utils:2": {},
    "ghcr.io/devcontainers-extra/features/node-asdf:0": {},
    "ghcr.io/devcontainers-extra/features/pnpm:2": {}
  },
  "postCreateCommand": "curl https://cursor.com/install -fsS | bash && echo 'export PATH=\"$HOME/.local/bin:$PATH\"' >> ~/.bashrc",
  "customizations": {
    "codespaces": {
      "openFiles": ["README.md"]
    }
  }
}
